torch_kde-0.1.5.dist-info/licenses/LICENSE
torchkde/__init__.py
torchkde/algorithms.py
torchkde/bandwidths.py
torchkde/kernels.py
torchkde/modules.py
torchkde/utils.py
torch_kde-0.1.5.dist-info/METADATA
torch_kde-0.1.5.dist-info/WHEEL
torch_kde-0.1.5.dist-info/top_level.txt
torch_kde-0.1.5.dist-info/RECORD
