Metadata-Version: 2.4
Name: torch-kde
Version: 0.1.5
Summary: A differentiable implementation of kernel density estimation in PyTorch
Author-email: Klaus-Rudolf Kladny <kkladny@tuebingen.mpg.de>
License: MIT
Project-URL: Homepage, https://github.com/rudolfwilliam/torch-kde
Keywords: density estimation,kde,pytorch,differentiable
Classifier: Programming Language :: Python :: 3
Classifier: License :: OSI Approved :: MIT License
Classifier: Operating System :: OS Independent
License-File: LICENSE
Requires-Dist: numpy>=2.2.0
Requires-Dist: scipy>=1.14.7
Requires-Dist: torch>=2.5.1
Dynamic: license-file
